pyams_thesaurus/__init__.py
pyams_thesaurus/include.py
pyams_thesaurus/index.py
pyams_thesaurus/manager.py
pyams_thesaurus/schema.py
pyams_thesaurus/term.py
pyams_thesaurus/thesaurus.py
pyams_thesaurus/api/__init__.py
pyams_thesaurus/api/rest.py
pyams_thesaurus/doctests/README.rst
pyams_thesaurus/doctests/data/SAMPLE-SKOS.xml
pyams_thesaurus/doctests/data/SAMPLE-Superdoc.xml
pyams_thesaurus/extension/__init__.py
pyams_thesaurus/extension/html/__init__.py
pyams_thesaurus/extension/html/interfaces.py
pyams_thesaurus/extension/html/zmi/__init__.py
pyams_thesaurus/generations/__init__.py
pyams_thesaurus/generations/evolve1.py
pyams_thesaurus/interfaces/__init__.py
pyams_thesaurus/interfaces/extension.py
pyams_thesaurus/interfaces/index.py
pyams_thesaurus/interfaces/loader.py
pyams_thesaurus/interfaces/term.py
pyams_thesaurus/interfaces/thesaurus.py
pyams_thesaurus/loader/__init__.py
pyams_thesaurus/loader/config.py
pyams_thesaurus/loader/skos.py
pyams_thesaurus/loader/superdoc.py
pyams_thesaurus/locales/pyams_thesaurus.pot
pyams_thesaurus/locales/fr/LC_MESSAGES/pyams_thesaurus.mo
pyams_thesaurus/locales/fr/LC_MESSAGES/pyams_thesaurus.po
pyams_thesaurus/tests/__init__.py
pyams_thesaurus/tests/test_utilsdocs.py
pyams_thesaurus/tests/test_utilsdocstrings.py
pyams_thesaurus/zmi/__init__.py
pyams_thesaurus/zmi/extension.py
pyams_thesaurus/zmi/extract.py
pyams_thesaurus/zmi/interfaces.py
pyams_thesaurus/zmi/term.py
pyams_thesaurus/zmi/test.py
pyams_thesaurus/zmi/thesaurus.py
pyams_thesaurus/zmi/tree.py
pyams_thesaurus/zmi/widget.py
pyams_thesaurus/zmi/resources/css/thesaurus.css
pyams_thesaurus/zmi/resources/css/thesaurus.min.css
pyams_thesaurus/zmi/resources/js/thesaurus.js
pyams_thesaurus/zmi/resources/js/thesaurus.min.js
pyams_thesaurus/zmi/resources/sass/thesaurus.scss
pyams_thesaurus/zmi/templates/extract-terms.pt
pyams_thesaurus/zmi/templates/terms-tree.pt
pyams_thesaurus/zmi/templates/widget/terms-tree-input.pt
pyams_thesaurus-2.2.0.dist-info/LICENSE
pyams_thesaurus-2.2.0.dist-info/METADATA
pyams_thesaurus-2.2.0.dist-info/WHEEL
pyams_thesaurus-2.2.0.dist-info/entry_points.txt
pyams_thesaurus-2.2.0.dist-info/namespace_packages.txt
pyams_thesaurus-2.2.0.dist-info/top_level.txt
pyams_thesaurus-2.2.0.dist-info/RECORD
