Metadata-Version: 2.1
Name: pyams-thesaurus
Version: 2.2.0
Summary: PyAMS thesaurus management package
Home-page: https://pyams.readthedocs.io
Author: Thierry Florac
Author-email: tflorac@ulthar.net
License: ZPL
Keywords: Pyramid PyAMS
Classifier: License :: OSI Approved :: Zope Public License
Classifier: Development Status :: 4 - Beta
Classifier: Programming Language :: Python
Classifier: Framework :: Pyramid
Classifier: Topic :: Software Development :: Libraries :: Python Modules
License-File: LICENSE
Requires-Dist: setuptools
Requires-Dist: chardet
Requires-Dist: colander
Requires-Dist: cornice
Requires-Dist: hypatia
Requires-Dist: lxml
Requires-Dist: persistent
Requires-Dist: pyams-catalog
Requires-Dist: pyams-file
Requires-Dist: pyams-i18n
Requires-Dist: pyams-security
Requires-Dist: pyams-site
Requires-Dist: pyams-utils
Requires-Dist: pyramid >=2.0.0
Requires-Dist: transaction
Requires-Dist: zope.annotation
Requires-Dist: zope.componentvocabulary
Requires-Dist: zope.container
Requires-Dist: zope.interface
Requires-Dist: zope.intid
Requires-Dist: zope.lifecycleevent
Requires-Dist: zope.location
Requires-Dist: zope.schema
Requires-Dist: zope.traversing
Provides-Extra: test
Requires-Dist: pyams-zmi ; extra == 'test'
Requires-Dist: pyramid-zcml ; extra == 'test'
Requires-Dist: zope.exceptions ; extra == 'test'
